disnake/ext/formatter/__init__.py
disnake_ext_formatter-0.1.0a1.dist-info/LICENSE
disnake_ext_formatter-0.1.0a1.dist-info/WHEEL
disnake_ext_formatter-0.1.0a1.dist-info/METADATA
disnake_ext_formatter-0.1.0a1.dist-info/RECORD
