Metadata-Version: 2.1
Name: disnake-ext-formatter
Version: 0.1.0a1
Summary: A simple string.Formatter for disnake types
License: MIT
Author: onerandomusername
Author-email: genericusername414@gmail.com
Requires-Python: >=3.8,<4.0
Classifier: License :: OSI Approved :: MIT License
Classifier: Programming Language :: Python :: 3
Classifier: Programming Language :: Python :: 3.10
Classifier: Programming Language :: Python :: 3.8
Classifier: Programming Language :: Python :: 3.9
Requires-Dist: disnake (>=2.0,<3.0)
